bad_passwords
