Metadata-Version: 2.4
Name: bad-passwords
Version: 1.0.1
Summary: Provides a single function for checking against commonly used passwords used by various Seantis packages.
Author-email: David Salvisberg <david.salvisberg@seantis.ch>
Maintainer-email: David Salvisberg <david.salvisberg@seantis.ch>
License-Expression: MIT
Project-URL: Repository, https://github.com/seantis/bad-passwords
Project-URL: Bug Tracker, http://github.com/seantis/bad-passwords/issues
Project-URL: Changelog, https://github.com/seantis/bad-passwords/blob/main/HISTORY.rst
Classifier: Framework :: Pytest
Classifier: Development Status :: 5 - Production/Stable
Classifier: Operating System :: OS Independent
Classifier: Programming Language :: Python
Classifier: Programming Language :: Python :: 3.10
Classifier: Programming Language :: Python :: 3.11
Classifier: Programming Language :: Python :: 3.12
Classifier: Programming Language :: Python :: 3.13
Classifier: Programming Language :: Python :: 3.14
Classifier: Programming Language :: Python :: 3 :: Only
Classifier: Programming Language :: Python :: Implementation :: CPython
Requires-Python: >=3.10
License-File: LICENSE
Provides-Extra: dev
Requires-Dist: bump-my-version; extra == "dev"
Requires-Dist: flake8; extra == "dev"
Requires-Dist: flake8-type-checking; extra == "dev"
Requires-Dist: flake8-pyproject; extra == "dev"
Requires-Dist: mypy; extra == "dev"
Requires-Dist: pre-commit; extra == "dev"
Requires-Dist: pre-commit-uv; extra == "dev"
Requires-Dist: pytest; extra == "dev"
Requires-Dist: requests; extra == "dev"
Requires-Dist: ruff; extra == "dev"
Requires-Dist: tox; extra == "dev"
Requires-Dist: tox-uv; extra == "dev"
Requires-Dist: types-requests; extra == "dev"
Requires-Dist: uv; extra == "dev"
Dynamic: license-file
